{
  "ref": "09 0505 70 16",
  "title": "M16 Connecteur mâle, Contacts: 16, 6,0-8,0 mm, non blindé, souder, IP67",
  "url": "https://www.binder-connector.com/fr/produits/miniatures/m16-ip67/09-0505-70-16-m16-ip67-connecteur-male-contacts-16-60-80-mm-non-blinde-souder-ip67",
  "family": "M16 IP67",
  "category1": "miniatures",
  "mainImage": null,
  "mainImageUrl": "https://www.binder-connector.com/prod_media/produktfoto_seo/723_1_25.jpg",
  "sections": {
    "Données techniques": {
      "Référence": "09 0505 70 16",
      "Design du connecteur": "Connecteur mâle",
      "Version": "Connecteur mâle droite",
      "Verrouillage du connecteur": "visser",
      "Connexion": "souder",
      "Indice de protection": "IP67",
      "Section de raccordement": "0,25 mm² / AWG 24",
      "Passage de câble": "6,0-8,0 mm",
      "Plage de températures de/à": "-40 °C / 95 °C",
      "Durée de vie mécanique": "> 500 Cycles d'accouplement",
      "Poids (g)": "37.75",
      "Numéro de tarif douanier": "85369010",
      "Pays d'origine": "DE",
      "Tension nominale": "60 V",
      "Tension de choc nominale": "500 V",
      "Courant nominal (40 °C)": "3,0 A",
      "Résistance d'isolation": "≥ 1010 Ω",
      "Degré d’encrassement": "1",
      "Catégorie de surtension": "I",
      "Groupe de matériau isolant": "III",
      "Conformité CEM": "non blindé",
      "Matériau du boîtier": "PA",
      "Matériau du corps de contact": "PBT (UL94 V-0)",
      "Matériau du contact": "CuZn (laiton)",
      "Revêtement du contact": "Au (or)",
      "REACH SVHC": "CAS 7439-92-1 (Lead)",
      "Numéro SCIP": "99eb5109-e552-4d8c-95b3-07652573ad88",
      "eCl@ss 11.1": "27-44-01-09",
      "ETIM 9.0": "EC003569",
      "Directive basse tension": "2014/35/EU (EN 60529:1991 | 2014/35/EU;EN 60204-1:2018)"
    }
  }
}