{
  "ref": "77 5430 0000 50704-0200",
  "title": "M8 Connecteur femelle, Contacts: 4, blindé, surmoulé sur le câble, IP67, Profinet/Ethernet CAT5e, PUR, vert, 4 x AWG 22, 2 m",
  "url": "https://www.binder-connector.com/fr/produits/connectique-dautomatisme-speciaux/m8-d/77-5430-0000-50704-0200-m8-d-connecteur-femelle-contacts-4-blinde-surmoule-sur-le-cable-ip67-ethernet-pur-vert-4-x-awg-22-2-m-1",
  "family": "M8-D",
  "category1": "connectique-dautomatisme-speciaux",
  "mainImage": null,
  "mainImageUrl": "https://www.binder-connector.com/prod_media/produktfoto_seo/818_2_KD-D_u_Ku.jpg",
  "sections": {
    "Données techniques": {
      "Référence": "77 5430 0000 50704-0200",
      "Design du connecteur": "Connecteur femelle",
      "Norme de conception": "DIN EN 61076-2-114",
      "Codage": "D-codé",
      "Longueur du câble": "2 m (Standard 2 m et 5 m. D'autres longueurs sont possibles sur demande.)",
      "Version": "Connecteur femelle droite",
      "Verrouillage du connecteur": "M8x1",
      "Connexion": "surmoulé sur le câble",
      "Indice de protection": "IP67",
      "Section de raccordement": "0,34 mm² / AWG 22",
      "Plage de températures de/à": "-25 °C / 85 °C",
      "Durée de vie mécanique": "> 100 Cycles d'accouplement",
      "Poids (g)": "269",
      "Numéro de tarif douanier": "85444290",
      "Pays d'origine": "DE",
      "Tension nominale": "63 V DC",
      "Tension de choc nominale": "1500 V",
      "Courant nominal (40 °C)": "4,0 A",
      "Résistance d'isolation": "> 108 Ω",
      "Degré d’encrassement": "3",
      "Catégorie de surtension": "II",
      "Groupe de matériau isolant": "I",
      "Conformité CEM": "blindé",
      "Raccordement du blindage": "Écran sur bague filetée",
      "Matériau du boîtier": "PUR",
      "Matériau du corps de contact": "PUR noir",
      "Matériau du contact": "CuZn (laiton)",
      "Revêtement du contact": "Au (or)",
      "Matériel de verrouillage": "CuZn (laiton)",
      "REACH SVHC": "CAS 7439-92-1 (Lead)",
      "Numéro SCIP": "044e3ab1-9fcd-4150-8bc1-fd354c7b3073",
      "Type de câble": "Profinet/Ethernet CAT5e",
      "Diamètre de câble": "6,7 mm",
      "Section transversale": "4 x AWG 22",
      "Matériau de la gaine": "PUR",
      "Isolation du toron": "Polyoléfine",
      "Couleur du câble": "vert",
      "Résistance du conducteur": "55 Ω/Km (20°C)",
      "Rayon de courbure de câble fixe": "≥ 5 x Ø",
      "Rayon de courbure de câble mobile": "≥ 15 x Ø",
      "Cycles de flexion": "2 millions",
      "Accélération admissible": "max. 2 m/s²",
      "Déplacement horizontal": "max. 5 m",
      "Déplacement vertical": "max. 5 m",
      "Vitesse de déplacement": "200 m/min",
      "Plage de temp. câble en mouvem. de/à": "-20 °C / 60 °C",
      "Plage de temp. câble fixe de/à": "-40 °C / 80 °C",
      "Sans halogène": "oui",
      "eCl@ss 11.1": "27-06-03-11",
      "ETIM 9.0": "EC002638"
    }
  }
}