{
  "ref": "99 3379 500 03",
  "title": "M8 Connecteur mâle, Contacts: 3, 2,5-5,0 mm, non blindé, IDC, IP67, UL",
  "url": "https://www.binder-connector.com/fr/produits/technologie-dautomatisation/m8/99-3379-500-03-m8-connecteur-male-contacts-3-25-50-mm-non-blinde-borne-de-coupure-ip67-ul",
  "family": "M8",
  "category1": "technologie-dautomatisation",
  "mainImage": null,
  "mainImageUrl": "https://www.binder-connector.com/prod_media/produktfoto_seo/768_1_KS_Schneid.jpg",
  "sections": {
    "Données techniques": {
      "Référence": "99 3379 500 03",
      "Design du connecteur": "Connecteur mâle",
      "Norme de conception": "DIN EN 61076-2-104",
      "Codage": "A-codé",
      "Version": "Connecteur mâle droite",
      "Verrouillage du connecteur": "visser",
      "Connexion": "IDC",
      "Indice de protection": "IP67",
      "Section de raccordement": "0,08-0,25 mm² / AWG 28-24",
      "Passage de câble": "2,5-5,0 mm",
      "Plage de températures de/à": "-25 °C / 85 °C",
      "Durée de vie mécanique": "> 100 Cycles d'accouplement",
      "Poids (g)": "5.67",
      "Numéro de tarif douanier": "85366990",
      "Pays d'origine": "DE",
      "Tension nominale": "60 V (UL 30 V)",
      "Tension de choc nominale": "1500 V",
      "Courant nominal (40 °C)": "4,0 A",
      "Degré d’encrassement": "3",
      "Catégorie de surtension": "III",
      "Groupe de matériau isolant": "III",
      "Conformité CEM": "non blindé",
      "Matériau du boîtier": "PA",
      "Matériau du corps de contact": "TPU",
      "Matériau du contact": "CuZn (laiton)",
      "Revêtement du contact": "Au (or)",
      "Matériel de verrouillage": "Zinc coulé sous pression nickelé",
      "REACH SVHC": "CAS 7439-92-1 (Lead)",
      "Numéro SCIP": "eb4e03bb-93ba-46bc-b328-fd5bcbc4dbb0",
      "eCl@ss 11.1": "27-44-01-02",
      "ETIM 9.0": "EC002635",
      "Directive basse tension": "2014/35/EU (EN 60529:1991 | 2014/35/EU;EN 60204-1:2018)"
    }
  }
}